streamlit_tags/__init__.py
streamlit_tags/frontend/build/asset-manifest.json
streamlit_tags/frontend/build/bootstrap.min.css
streamlit_tags/frontend/build/index.html
streamlit_tags/frontend/build/precache-manifest.0c767461934bf250de2fd6500d7e6ee1.js
streamlit_tags/frontend/build/precache-manifest.25a1a66f7419e48f9c0c228e68c9236a.js
streamlit_tags/frontend/build/precache-manifest.46144d24a5919916ef88e336e27e04be.js
streamlit_tags/frontend/build/precache-manifest.464268395184bb9e04ec039b34147b80.js
streamlit_tags/frontend/build/precache-manifest.4939776342627c7555648c460ab971ea.js
streamlit_tags/frontend/build/precache-manifest.6222cbe265874cb6f55f5791697621db.js
streamlit_tags/frontend/build/precache-manifest.75396fb61a7703af235c7d10f2cc220f.js
streamlit_tags/frontend/build/precache-manifest.8d1355061dfb5c15fa559226bc2bd445.js
streamlit_tags/frontend/build/precache-manifest.d407d9bf26efe93b38748da8127a8250.js
streamlit_tags/frontend/build/service-worker.js
streamlit_tags/frontend/build/static/css/main.07950e13.chunk.css
streamlit_tags/frontend/build/static/css/main.07950e13.chunk.css.map
streamlit_tags/frontend/build/static/css/main.12f84a3d.chunk.css
streamlit_tags/frontend/build/static/css/main.12f84a3d.chunk.css.map
streamlit_tags/frontend/build/static/css/main.52c07994.chunk.css
streamlit_tags/frontend/build/static/css/main.52c07994.chunk.css.map
streamlit_tags/frontend/build/static/css/main.5a34966d.chunk.css
streamlit_tags/frontend/build/static/css/main.5a34966d.chunk.css.map
streamlit_tags/frontend/build/static/css/main.5b6c2ff8.chunk.css
streamlit_tags/frontend/build/static/css/main.5b6c2ff8.chunk.css.map
streamlit_tags/frontend/build/static/css/main.70de92d6.chunk.css
streamlit_tags/frontend/build/static/css/main.70de92d6.chunk.css.map
streamlit_tags/frontend/build/static/css/main.dd00a657.chunk.css
streamlit_tags/frontend/build/static/css/main.dd00a657.chunk.css.map
streamlit_tags/frontend/build/static/js/2.6d7de458.chunk.js
streamlit_tags-1.2.8.dist-info/LICENSE.txt
streamlit_tags-1.2.8.dist-info/METADATA
streamlit_tags-1.2.8.dist-info/WHEEL
streamlit_tags-1.2.8.dist-info/top_level.txt
streamlit_tags-1.2.8.dist-info/RECORD
