Metadata-Version: 2.1
Name: streamlit_tags
Version: 1.2.8
Summary: Tags custom component for Streamlit
Home-page: https://github.com/gagan3012/streamlit-tags
Author: Gagan Bhatia
Author-email: gbhatia880@gmail.com
License: MIT
Platform: UNKNOWN
Requires-Python: >=3.6
